CHANGES.rst
MANIFEST.in
README.rst
setup.py
pltk/__init__.py
pltk/logger.py
pltk.egg-info/PKG-INFO
pltk.egg-info/SOURCES.txt
pltk.egg-info/dependency_links.txt
pltk.egg-info/not-zip-safe
pltk.egg-info/requires.txt
pltk.egg-info/top_level.txt
pltk/flask_utils/__init__.py
pltk/flask_utils/commands.py
pltk/flask_utils/limit.py
pltk/flask_utils/locale.py
pltk/flask_utils/monitor_command.py
pltk/flask_utils/redis_wrapper.py
pltk/flask_utils/tests.py
pltk/flask_utils/view.py
tests/__init__.py
tests/test_flask_utils/__init__.py
tests/test_flask_utils/test_commands.py
tests/test_flask_utils/test_view.py