Metadata-Version: 1.0
Name: pltk
Version: 0.3
Summary: Paylogic Toolkit
Home-page: UNKNOWN
Author: Paylogic International
Author-email: developers@paylogic.com
License: MIT
Platform: UNKNOWN
